lox/__init__.py
lox/debug.py
lox/exceptions.py
lox/helper.py
lox/py.typed
lox/lock/__init__.py
lox/lock/index_semaphore.py
lox/lock/light_switch.py
lox/lock/qlock.py
lox/lock/rw_lock.py
lox/queue/__init__.py
lox/queue/announcement.py
lox/queue/funnel.py
lox/worker/__init__.py
lox/worker/process.py
lox/worker/thread.py
lox-1.0.0.dist-info/AUTHORS.rst
lox-1.0.0.dist-info/LICENSE
lox-1.0.0.dist-info/METADATA
lox-1.0.0.dist-info/WHEEL
lox-1.0.0.dist-info/top_level.txt
lox-1.0.0.dist-info/RECORD
