Metadata-Version: 2.1
Name: lox
Version: 1.0.0
Summary: Threading and Multiprocessing for every project.
Home-page: https://github.com/BrianPugh/lox
Author: Brian Pugh
Author-email: bnp117@gmail.com
License: MIT license
Keywords: lox
Classifier: Development Status :: 2 - Pre-Alpha
Classifier: Intended Audience :: Developers
Classifier: License :: OSI Approved :: MIT License
Classifier: Natural Language :: English
Classifier: Programming Language :: Python :: 3
Classifier: Programming Language :: Python :: 3.8
Classifier: Programming Language :: Python :: 3.9
Classifier: Programming Language :: Python :: 3.10
Classifier: Programming Language :: Python :: 3.11
Classifier: Programming Language :: Python :: 3.12
License-File: LICENSE
License-File: AUTHORS.rst
Provides-Extra: multiprocessing
Requires-Dist: pathos; extra == "multiprocessing"
